sdat/__init__.py
sdat/pipeline.py
sdat/sdat_align.py
sdat/sdat_cell.py
sdat/sdat_count.py
sdat/sdat_filter.py
sdat/tmp.py
sdat/tools_bc/__init__.py
sdat/tools_bc/barcode1.py
sdat/tools_bc/barcode2.py
sdat/tools_bc/barcode3.py
sdat/tools_bc/barcode_index.py
sdat/tools_bc/barcode_listbc.py
sdat/tools_bc/barcode_to_cell.py
sdat/tools_bc/barcode_to_cell_nomix.py
sdat/tools_bc/barcode_to_round_id.py
sdat/tools_count/__init__.py
sdat/tools_count/count_gene_per_cell.py
sdat/tools_count/count_profile.py
sdat/tools_count/get_expression_table.py
sdat/tools_count/overall_count.py
sdat/tools_fq/__init__.py
sdat/tools_fq/filter_fq.py
sdat/tools_fq/split_fq.py
sdat/tools_fq/split_fqgzip.py
sdat/tools_merge/__init__.py
sdat/tools_merge/merge_barcode.py
sdat/tools_merge/merge_cell.py
sdat/tools_merge/merge_cell_log.py
sdat/tools_merge/merge_fastq.py
sdat/tools_merge/merge_filter_ratio.py
sdat/tools_merge/merge_reads_per_cell.py
sdat/tools_merge/merge_rmdup_log.py
sdat/tools_merge/merge_sam.py
sdat/tools_sam/__init__.py
sdat/tools_sam/sam_rmdup.py
sdat/tools_sam/split_bam.py
sdat/tools_sam/split_sam.py
sdat/tools_sam/split_sam_to_cell.py
sdat-0.1.6.dist-info/METADATA
sdat-0.1.6.dist-info/WHEEL
sdat-0.1.6.dist-info/entry_points.txt
sdat-0.1.6.dist-info/top_level.txt
sdat-0.1.6.dist-info/RECORD
