Metadata-Version: 1.1
Name: sdat
Version: 0.1.6
Summary: A toolkit for analysing SPLiT-seq data
Home-page: https://github.com/Chipeyown/SPLiT-seq-Data-Analysis_Toolkit
Author: Chipeyown
Author-email: chipeyown@gmail.com
License: MIT
Keywords: SPLiT-seq
Platform: UNKNOWN
Classifier: Development Status :: 3 - Alpha
Classifier: Programming Language :: Python :: 2
Classifier: Programming Language :: Python :: 3
